[
    {
        "slot": {
            "period": 0,
            "thread": 0
        },
        "execution_steps": [
            {
                "name": "setup_initial_address",
                "config": {
                    "type": "write_ledger_entry",
                    "address": "X6Jqk749Dk8=",
                    "balance": 200000
                }
            },
            {
                "name": "simple_step_name",
                "config": {
                    "type": "execute_sc",
                    "path": "../massa-sc-examples/async-calls/build/main.wasm",
                    "gas": 100000,
                    "call_stack": [
                        {
                            "address": "X6Jqk749Dk8=",
                            "coins": 100
                        }
                    ]
                }
            }
        ]
    }
]